spotify_playlist_additions_core/__init__.py
spotify_playlist_additions_core/cli.py
spotify_playlist_additions_core/spotify_playlist_additions_core.py
spotify_playlist_additions_core-0.1.3.dist-info/AUTHORS.md
spotify_playlist_additions_core-0.1.3.dist-info/LICENSE
spotify_playlist_additions_core-0.1.3.dist-info/METADATA
spotify_playlist_additions_core-0.1.3.dist-info/WHEEL
spotify_playlist_additions_core-0.1.3.dist-info/entry_points.txt
spotify_playlist_additions_core-0.1.3.dist-info/top_level.txt
spotify_playlist_additions_core-0.1.3.dist-info/RECORD
