Metadata-Version: 2.1
Name: spotify-playlist-additions-core
Version: 0.1.3
Summary: Core runner for Spotify Playlist Additions. Where all the magic happens
Home-page: https://github.com/prchristie/spotify-playlist-additions-core
Author: Patrick Roy Christie
Author-email: patrick.christie.dev@gmail.com
License: MIT license
Keywords: spotify_playlist_additions_core
Platform: UNKNOWN
Classifier: Development Status :: 2 - Pre-Alpha
Classifier: Intended Audience :: Developers
Classifier: License :: OSI Approved :: MIT License
Classifier: Natural Language :: English
Classifier: Programming Language :: Python :: 3
Classifier: Programming Language :: Python :: 3.6
Classifier: Programming Language :: Python :: 3.7
Classifier: Programming Language :: Python :: 3.8
Requires-Python: >=3.6
License-File: LICENSE
License-File: AUTHORS.md
